pypi.py
frompypi-0.3.dist-info/METADATA
frompypi-0.3.dist-info/WHEEL
frompypi-0.3.dist-info/top_level.txt
frompypi-0.3.dist-info/RECORD
