Metadata-Version: 2.1
Name: frompypi
Version: 0.3
Summary: from pypy import anything
Home-page: http://github.com/orent/frompypy
Author: Oren Tirosh
Author-email: orent@hishome.net
License: UNKNOWN
Platform: UNKNOWN
